ReSpider/VERSION
ReSpider/__init__.py
ReSpider/__main__.py
ReSpider/dupefilter.py
ReSpider/item.py
ReSpider/notify.py
ReSpider/setting.py
ReSpider/cmd/__init__.py
ReSpider/cmd/cmdline.py
ReSpider/cmd/create_builder.py
ReSpider/cmd/create/__init__.py
ReSpider/cmd/create/create_init.py
ReSpider/cmd/create/create_project.py
ReSpider/cmd/create/create_setting.py
ReSpider/cmd/create/create_spider.py
ReSpider/core/__init__.py
ReSpider/core/engine.py
ReSpider/core/observer.py
ReSpider/core/scheduler.py
ReSpider/core/buffer/__init__.py
ReSpider/core/buffer/item_buffer.py
ReSpider/core/buffer/request_buffer.py
ReSpider/core/downloader/__init__.py
ReSpider/core/downloader/_ssl.py
ReSpider/core/downloader/handlers.py
ReSpider/core/downloader/middleware.py
ReSpider/core/queue/__init__.py
ReSpider/core/spiders/__init__.py
ReSpider/core/spiders/spider.py
ReSpider/db/__init__.py
ReSpider/db/mongodb.py
ReSpider/db/mysqldb.py
ReSpider/db/redisdb.py
ReSpider/extend/__init__.py
ReSpider/extend/filter.py
ReSpider/extend/misc.py
ReSpider/extend/setting_loader.py
ReSpider/extend/token_bucket.py
ReSpider/extend/logger/__init__.py
ReSpider/extend/logger/log_mixin.py
ReSpider/extend/notify/__init__.py
ReSpider/extend/notify/dingtalk.py
ReSpider/extend/notify/style.py
ReSpider/extend/puppeteer/__init__.py
ReSpider/extend/puppeteer/downloadmiddleware.py
ReSpider/extend/puppeteer/request.py
ReSpider/extend/puppeteer/response.py
ReSpider/extend/puppeteer/settings.py
ReSpider/extend/redis/__init__.py
ReSpider/extend/redis/dupefilter.py
ReSpider/extend/redis/scheduler.py
ReSpider/extend/redis/spider.py
ReSpider/http/__init__.py
ReSpider/http/request.py
ReSpider/http/response.py
ReSpider/middlewares/__init__.py
ReSpider/middlewares/cookies.py
ReSpider/middlewares/httperror.py
ReSpider/middlewares/proxy.py
ReSpider/middlewares/retry.py
ReSpider/middlewares/useragent.py
ReSpider/pipelines/__init__.py
ReSpider/pipelines/file.py
ReSpider/pipelines/mongo.py
ReSpider/pipelines/mysql.py
ReSpider-1.0.4.dist-info/LICENSE
ReSpider-1.0.4.dist-info/METADATA
ReSpider-1.0.4.dist-info/WHEEL
ReSpider-1.0.4.dist-info/entry_points.txt
ReSpider-1.0.4.dist-info/top_level.txt
ReSpider-1.0.4.dist-info/RECORD
