Metadata-Version: 2.1
Name: ReSpider
Version: 1.0.4
Summary: ReSpider是一款基于 aiohttp 请求库的python爬虫程序
Home-page: https://github.com/zaoxg/ReSpiderFramework
Author: zhaoxiangpeng
Author-email: zhaoxiangpengSR@gmail.com
Project-URL: Bug Tracker, https://github.com/zaoxg/ReSpiderFramework/issues
Keywords: respider
Classifier: Programming Language :: Python :: 3
Requires-Python: >=3.7
License-File: LICENSE
Requires-Dist: urllib3 (==1.25.8)
Requires-Dist: requests (==2.22.0)
Requires-Dist: aiohttp (>=3.7.3)
Requires-Dist: cchardet (>=2.1.7)
Requires-Dist: parsel (>=1.6.0)
Requires-Dist: aiofiles (>=0.6.0)
Requires-Dist: aiocsv (>=1.2.1)
Requires-Dist: redis (<4.0.0,>=2.10.6)
Requires-Dist: pymongo (>=3.11.2)
Requires-Dist: motor (>=2.3.1)
Requires-Dist: PyMySQL (>=0.9.3)
Requires-Dist: aiomysql (>=0.0.21)
Requires-Dist: pyppeteer (>=0.2.5)
Requires-Dist: PyExecJS (>=1.5.1)
